{
  "nodes": [
    "Ballari, Karnataka, India",
    "Hospet, Karnataka, India",
    "Hubballi, Karnataka, India",
    "Bengaluru, Karnataka, India",
    "Hyderabad, Telangana, India",
    "Kurnool, Andhra Pradesh, India",
    "Chitradurga, Karnataka, India",
    "Chennai, Tamil Nadu, India",
    "Kochi, Kerala, India",
    "Thiruvananthapuram, Kerala, India",
    "Visakhapatnam, Andhra Pradesh, India",
    "Mumbai, Maharashtra, India",
    "Pune, Maharashtra, India",
    "Ahmedabad, Gujarat, India",
    "New Delhi, India",
    "Jaipur, Rajasthan, India",
    "Lucknow, Uttar Pradesh, India",
    "Kolkata, West Bengal, India",
    "Bhubaneswar, Odisha, India",
    "Patna, Bihar, India",
    "Indore, Madhya Pradesh, India",
    "Nagpur, Maharashtra, India",
    "Guwahati, Assam, India",
    "Tirupati, Andhra Pradesh, India",
    "Amritsar, Punjab, India",
    "Surat, Gujarat, India",
    "Vadodara, Gujarat, India",
    "Nashik, Maharashtra, India",
    "Bhopal, Madhya Pradesh, India",
    "Kanpur, Uttar Pradesh, India",
    "Varanasi, Uttar Pradesh, India",
    "Coimbatore, Tamil Nadu, India",
    "Madurai, Tamil Nadu, India",
    "Vijayawada, Andhra Pradesh, India",
    "Kozhikode, Kerala, India",
    "Chandigarh, India",
    "Srinagar, Jammu and Kashmir, India",
    "Leh, Ladakh, India",
    "Panaji, Goa, India",
    "Mangalore, Karnataka, India",
    "Mysuru, Karnataka, India",
    "Agra, Uttar Pradesh, India",
    "Ranchi, Jharkhand, India",
    "Raipur, Chhattisgarh, India",
    "Dehradun, Uttarakhand, India",
    "Shimla, Himachal Pradesh, India"
  ],
  "edges": [
    { "source": "Ballari, Karnataka, India", "target": "Hospet, Karnataka, India", "weight": 1.0 },
    { "source": "Hospet, Karnataka, India", "target": "Ballari, Karnataka, India", "weight": 1.0 },

    { "source": "Ballari, Karnataka, India", "target": "Chitradurga, Karnataka, India", "weight": 2.5 },
    { "source": "Chitradurga, Karnataka, India", "target": "Bengaluru, Karnataka, India", "weight": 3.0 },
    { "source": "Bengaluru, Karnataka, India", "target": "Mysuru, Karnataka, India", "weight": 3.0 },
    { "source": "Bengaluru, Karnataka, India", "target": "Chennai, Tamil Nadu, India", "weight": 6.0 },
    { "source": "Chennai, Tamil Nadu, India", "target": "Tirupati, Andhra Pradesh, India", "weight": 4.0 },
    { "source": "Tirupati, Andhra Pradesh, India", "target": "Vijayawada, Andhra Pradesh, India", "weight": 6.0 },
    { "source": "Vijayawada, Andhra Pradesh, India", "target": "Visakhapatnam, Andhra Pradesh, India", "weight": 7.0 },
    { "source": "Visakhapatnam, Andhra Pradesh, India", "target": "Bhubaneswar, Odisha, India", "weight": 7.5 },
    { "source": "Bhubaneswar, Odisha, India", "target": "Kolkata, West Bengal, India", "weight": 7.0 },
    { "source": "Kolkata, West Bengal, India", "target": "Patna, Bihar, India", "weight": 8.0 },
    { "source": "Patna, Bihar, India", "target": "Varanasi, Uttar Pradesh, India", "weight": 5.0 },
    { "source": "Varanasi, Uttar Pradesh, India", "target": "Lucknow, Uttar Pradesh, India", "weight": 5.0 },
    { "source": "Lucknow, Uttar Pradesh, India", "target": "Kanpur, Uttar Pradesh, India", "weight": 2.0 },
    { "source": "Kanpur, Uttar Pradesh, India", "target": "Agra, Uttar Pradesh, India", "weight": 5.0 },
    { "source": "Agra, Uttar Pradesh, India", "target": "New Delhi, India", "weight": 4.0 },
    { "source": "New Delhi, India", "target": "Jaipur, Rajasthan, India", "weight": 5.0 },
    { "source": "Jaipur, Rajasthan, India", "target": "Ahmedabad, Gujarat, India", "weight": 9.0 },
    { "source": "Ahmedabad, Gujarat, India", "target": "Vadodara, Gujarat, India", "weight": 2.0 },
    { "source": "Vadodara, Gujarat, India", "target": "Surat, Gujarat, India", "weight": 3.0 },
    { "source": "Surat, Gujarat, India", "target": "Mumbai, Maharashtra, India", "weight": 5.0 },
    { "source": "Mumbai, Maharashtra, India", "target": "Pune, Maharashtra, India", "weight": 3.0 },
    { "source": "Pune, Maharashtra, India", "target": "Goa, India", "weight": 8.0 },
    { "source": "Goa, India", "target": "Mangalore, Karnataka, India", "weight": 5.0 },
    { "source": "Mangalore, Karnataka, India", "target": "Kozhikode, Kerala, India", "weight": 5.0 },
    { "source": "Kozhikode, Kerala, India", "target": "Kochi, Kerala, India", "weight": 4.0 },
    { "source": "Kochi, Kerala, India", "target": "Thiruvananthapuram, Kerala, India", "weight": 5.0 },
    { "source": "New Delhi, India", "target": "Chandigarh, India", "weight": 4.5 },
    { "source": "Chandigarh, India", "target": "Shimla, Himachal Pradesh, India", "weight": 3.0 },
    { "source": "Chandigarh, India", "target": "Amritsar, Punjab, India", "weight": 4.0 },
    { "source": "Amritsar, Punjab, India", "target": "Srinagar, Jammu and Kashmir, India", "weight": 8.0 },
    { "source": "Srinagar, Jammu and Kashmir, India", "target": "Leh, Ladakh, India", "weight": 12.0 },
    { "source": "Bhopal, Madhya Pradesh, India", "target": "Indore, Madhya Pradesh, India", "weight": 3.0 },
    { "source": "Bhopal, Madhya Pradesh, India", "target": "Nagpur, Maharashtra, India", "weight": 5.0 },
    { "source": "Nagpur, Maharashtra, India", "target": "Hyderabad, Telangana, India", "weight": 8.0 },
    { "source": "Hyderabad, Telangana, India", "target": "Bengaluru, Karnataka, India", "weight": 9.0 },
    { "source": "Hyderabad, Telangana, India", "target": "Raipur, Chhattisgarh, India", "weight": 7.0 },
    { "source": "Raipur, Chhattisgarh, India", "target": "Ranchi, Jharkhand, India", "weight": 7.0 },
    { "source": "Ranchi, Jharkhand, India", "target": "Patna, Bihar, India", "weight": 4.0 },
    { "source": "Dehradun, Uttarakhand, India", "target": "New Delhi, India", "weight": 5.0 }
  ]
}
